djutils_auth/__init__.py
djutils_auth-0.1.0.dev0.dist-info/LICENSE
djutils_auth-0.1.0.dev0.dist-info/METADATA
djutils_auth-0.1.0.dev0.dist-info/WHEEL
djutils_auth-0.1.0.dev0.dist-info/top_level.txt
djutils_auth-0.1.0.dev0.dist-info/RECORD
